[
  {
    "avatar": "https://cdn-icons-png.flaticon.com/512/147/147142.png",
    "name": "Pioter",
    "isOnline": true,
    "id": 1
  },
  {
    "avatar": "https://cdn-icons-png.flaticon.com/512/1999/1999628.png",
    "name": "Krycha",
    "isOnline": false,
    "id": 2
  },
  {
    "avatar": "https://cdn-icons.flaticon.com/png/512/4140/premium/4140051.png?token=exp=1644084991~hmac=5f627538fee018077ae0abe2bc5d38ac",
    "name": "Andzia",
    "isOnline": true,
    "id": 3
  },
  {
    "avatar": "https://cdn-icons-png.flaticon.com/512/1999/1999625.png",
    "name": "Stachu",
    "isOnline": false,
    "id": 4
  },
  {
    "avatar": "https://cdn-icons.flaticon.com/png/512/4140/premium/4140047.png?token=exp=1644084975~hmac=46dd78c149dd5da1fac3effb78c0e3c1",
    "name": "Grażyna",
    "isOnline": false,
    "id": 5
  },
  {
    "avatar": "https://cdn-icons-png.flaticon.com/512/147/147144.png",
    "name": "Walduś",
    "isOnline": true,
    "id": 6
  }
]
